tensorflow_addons-0.23.0.dist-info/RECORD
tensorflow_addons-0.23.0.dist-info/LICENSE
tensorflow_addons-0.23.0.dist-info/WHEEL
tensorflow_addons-0.23.0.dist-info/top_level.txt
tensorflow_addons-0.23.0.dist-info/METADATA
tensorflow_addons.dylibs/libtensorflow_framework.2.dylib
tensorflow_addons-0.23.0.data/purelib/tensorflow_addons/options.py
tensorflow_addons-0.23.0.data/purelib/tensorflow_addons/conftest.py
tensorflow_addons-0.23.0.data/purelib/tensorflow_addons/version.py
tensorflow_addons-0.23.0.data/purelib/tensorflow_addons/register.py
tensorflow_addons-0.23.0.data/purelib/tensorflow_addons/__init__.py
tensorflow_addons-0.23.0.data/purelib/tensorflow_addons/activations/lisht.py
tensorflow_addons-0.23.0.data/purelib/tensorflow_addons/activations/tanhshrink.py
tensorflow_addons-0.23.0.data/purelib/tensorflow_addons/activations/sparsemax.py
tensorflow_addons-0.23.0.data/purelib/tensorflow_addons/activations/gelu.py
tensorflow_addons-0.23.0.data/purelib/tensorflow_addons/activations/softshrink.py
tensorflow_addons-0.23.0.data/purelib/tensorflow_addons/activations/mish.py
tensorflow_addons-0.23.0.data/purelib/tensorflow_addons/activations/__init__.py
tensorflow_addons-0.23.0.data/purelib/tensorflow_addons/activations/snake.py
tensorflow_addons-0.23.0.data/purelib/tensorflow_addons/activations/hardshrink.py
tensorflow_addons-0.23.0.data/purelib/tensorflow_addons/activations/rrelu.py
tensorflow_addons-0.23.0.data/purelib/tensorflow_addons/metrics/matthews_correlation_coefficient.py
tensorflow_addons-0.23.0.data/purelib/tensorflow_addons/metrics/multilabel_confusion_matrix.py
tensorflow_addons-0.23.0.data/purelib/tensorflow_addons/metrics/cohens_kappa.py
tensorflow_addons-0.23.0.data/purelib/tensorflow_addons/metrics/streaming_correlations.py
tensorflow_addons-0.23.0.data/purelib/tensorflow_addons/metrics/__init__.py
tensorflow_addons-0.23.0.data/purelib/tensorflow_addons/metrics/utils.py
tensorflow_addons-0.23.0.data/purelib/tensorflow_addons/metrics/f_scores.py
tensorflow_addons-0.23.0.data/purelib/tensorflow_addons/metrics/geometric_mean.py
tensorflow_addons-0.23.0.data/purelib/tensorflow_addons/metrics/hamming.py
